MANIFEST.in
README.txt
setup.py
collective/__init__.py
collective.stickyitem.egg-info/PKG-INFO
collective.stickyitem.egg-info/SOURCES.txt
collective.stickyitem.egg-info/dependency_links.txt
collective.stickyitem.egg-info/entry_points.txt
collective.stickyitem.egg-info/namespace_packages.txt
collective.stickyitem.egg-info/not-zip-safe
collective.stickyitem.egg-info/requires.txt
collective.stickyitem.egg-info/top_level.txt
collective/stickyitem/__init__.py
collective/stickyitem/configure.zcml
collective/stickyitem/schemaextender.py
collective/stickyitem/setuphandlers.py
collective/stickyitem/tests.py
collective/stickyitem/Extensions/Install.py
collective/stickyitem/locales/collective.stickyitem.pot
collective/stickyitem/locales/da/LC_MESSAGES/collective.stickyitem.po
collective/stickyitem/profiles/default/componentregistry.xml
collective/stickyitem/profiles/default/default
collective/stickyitem/profiles/default/metadata.xml
collective/stickyitem/profiles/uninstall/import_steps.xml
collective/stickyitem/profiles/uninstall/stickyitem_uninstall.txt
docs/HISTORY.txt
docs/INSTALL.txt
docs/LICENSE.GPL
docs/LICENSE.txt