Metadata-Version: 1.0
Name: collective.stickyitem
Version: 1.0.4
Summary: UNKNOWN
Home-page: http://svn.plone.org/svn/collective/collective.stickyitem
Author: Roman Kozlovskiy
Author-email: support@quintagroup.com
License: GPL
Platform: UNKNOWN
Classifier: Framework :: Plone
Classifier: Programming Language :: Python
